carp_api/VERSION
carp_api/__init__.py
carp_api/__main__.py
carp_api/api_request.py
carp_api/auth_model.py
carp_api/cli.py
carp_api/datetime_helper.py
carp_api/endpoint.py
carp_api/exception.py
carp_api/misc_helper.py
carp_api/request_parser.py
carp_api/signal.py
carp_api/url.py
carp_api/validator.py
carp_api/common/__init__.py
carp_api/common/endpoint.py
carp_api/common/logic.py
carp_api/data/favicon.png
carp_api/routing/__init__.py
carp_api/routing/component.py
carp_api/routing/helper.py
carp_api/routing/router.py
carp_api/server_factory/__init__.py
carp_api/server_factory/app.py
carp_api/server_factory/default.py
carp_api/server_factory/server_factory.py
carp_api/settings/__init__.py
carp_api/settings/base.py
carp_api/settings/flask_defaults.py
tests/__init__.py
tests/test_app.py
tests/test_request_parsing.py
tests/test_router.py
tests/test_routing_building.py
tests/test_versions.py
carp_api-0.1.1.dist-info/LICENSE
carp_api-0.1.1.dist-info/METADATA
carp_api-0.1.1.dist-info/WHEEL
carp_api-0.1.1.dist-info/entry_points.txt
carp_api-0.1.1.dist-info/top_level.txt
carp_api-0.1.1.dist-info/RECORD
