Metadata-Version: 2.1
Name: carp-api
Version: 0.1.1
Summary: Carp-Api is an extension on top of flask micro-framework, it allows to build endpoints and sort outs exception handling. Allowing developers to just start coding restful-api and not be concerned by standard and mundane fuff.
Home-page: https://github.com/Drachenfels/carp-api
Author: Drachenfels <drachenfels@protonmail.com>
Author-email: drachenfels@protonmail.com
License: MIT
Platform: UNKNOWN
Classifier: Development Status :: 4 - Beta
Classifier: License :: OSI Approved :: MIT License
Classifier: Intended Audience :: Developers
Classifier: Programming Language :: Python :: 3 :: Only
Classifier: Programming Language :: Python :: 3.7
Classifier: Topic :: Software Development :: Version Control :: Git
Requires-Dist: Flask (>=1.0)
Requires-Dist: blinker (>=1.4)
Requires-Dist: simple-settings (>=0.13)
Requires-Dist: python-dateutil (>=2.7)
Requires-Dist: pytz (>=2018.4)
Requires-Dist: url2vapi (>=1.2)
Requires-Dist: validators (>=0.12)
Requires-Dist: python-schema (>=0.4.1)
